bibcite/__init__.py
bibcite/cli.py
bibcite/work.py
bibcite-0.2.3.dist-info/METADATA
bibcite-0.2.3.dist-info/WHEEL
bibcite-0.2.3.dist-info/entry_points.txt
bibcite-0.2.3.dist-info/top_level.txt
bibcite-0.2.3.dist-info/RECORD
