Metadata-Version: 2.1
Name: bibcite
Version: 0.2.3
Summary: Generate bibtex citations from command line and instantly copies them to clipboard
Author-email: Daniel Hollarek <daniel.hollarek@googlemail.com>
Requires-Dist: requests
Requires-Dist: pyperclip
Requires-Dist: tabulate
